Metadata-Version: 2.1
Name: VLCDA
Version: 1.0.10
Summary: Python module dedicated to the evolution of logic circuits through genetic algorithms
Home-page: https://github.com/HumbertoTavora/Logic-Circuits-Evolution
Download-URL: https://github.com/HumbertoTavora/Logic-Circuits-Evolution
Author: Humberto Távora, Stefan Blawid, Yasmin Maria
Author-email: humbertocctg@gmail.com
License: MIT
Keywords: Genetic,Algorithm,Logic Circuits,Evolution,Optimization
Classifier: Programming Language :: Python :: 3
Classifier: Intended Audience :: Developers
License-File: LICENSE.txt
